ibis_bigquery/__init__.py
ibis_bigquery/backports.py
ibis_bigquery/client.py
ibis_bigquery/compiler.py
ibis_bigquery/datatypes.py
ibis_bigquery/operations.py
ibis_bigquery/registry.py
ibis_bigquery/rewrites.py
ibis_bigquery/version.py
ibis_bigquery/tests/__init__.py
ibis_bigquery/tests/conftest.py
ibis_bigquery/udf/__init__.py
ibis_bigquery/udf/core.py
ibis_bigquery/udf/find.py
ibis_bigquery/udf/rewrite.py
ibis_bigquery-2.2.1.dist-info/LICENSE
ibis_bigquery-2.2.1.dist-info/METADATA
ibis_bigquery-2.2.1.dist-info/WHEEL
ibis_bigquery-2.2.1.dist-info/entry_points.txt
ibis_bigquery-2.2.1.dist-info/top_level.txt
ibis_bigquery-2.2.1.dist-info/RECORD
