Metadata-Version: 2.1
Name: ibis-bigquery
Version: 2.2.1
Summary: Ibis BigQuery backend
Home-page: https://github.com/ibis-project/ibis-bigquery
Author: Ibis Contributors
Maintainer: Tim Swast
Maintainer-email: swast@google.com
License: Apache 2.0
Classifier: Development Status :: 5 - Production/Stable
Classifier: Operating System :: OS Independent
Classifier: Intended Audience :: Science/Research
Classifier: Programming Language :: Python
Classifier: Programming Language :: Python :: 3
Classifier: Topic :: Scientific/Engineering
Requires-Python: >=3.7
License-File: LICENSE
Requires-Dist: ibis-framework (<4.0.0dev,>=2.0.0)
Requires-Dist: db-dtypes (<2.0.0dev,>=0.3.0)
Requires-Dist: google-cloud-bigquery (<4.0.0dev,>=1.12.0)
Requires-Dist: google-cloud-bigquery-storage (<3.0.0dev,>=1.0.0)
Requires-Dist: packaging (>=17.0)
Requires-Dist: pyarrow (<10.0.0dev,>=1.0.0)
Requires-Dist: pydata-google-auth
Requires-Dist: sqlalchemy (<2.0,>=1.4)
